j1bz
