Metadata-Version: 1.1
Name: j1bz.expression
Version: 0.0.4
Summary: DSL intended to express requests for b3j0f.crudity.
Home-page: https://github.com/j1bz/expression
Author: j1bz
Author-email: jbaptiste.braun@gmail.com
License: MIT License
Download-URL: https://github.com/j1bz/expression/tarball/0.0.4
Keywords: expression,crudity,dsl,query,system,access,data,crud,create,delete,update,read,request,grako
Platform: UNKNOWN
Classifier: Development Status :: 4 - Beta
Classifier: License :: OSI Approved :: MIT License
Classifier: Natural Language :: French
Classifier: Operating System :: OS Independent
Classifier: Topic :: Utilities
Classifier: Topic :: Software Development
Classifier: Intended Audience :: Developers
Classifier: Programming Language :: Python
Classifier: Programming Language :: Python :: 2.6
Classifier: Programming Language :: Python :: 2.7
Classifier: Programming Language :: Python :: 3
Classifier: Programming Language :: Python :: 3.0
Classifier: Programming Language :: Python :: 3.1
Classifier: Programming Language :: Python :: 3.2
Classifier: Programming Language :: Python :: 3.3
Classifier: Programming Language :: Python :: 3.4
Classifier: Programming Language :: Python :: 3.5
Classifier: Programming Language :: Python :: Implementation :: CPython
